[[{"__type__":"cc.Prefab","_name":"suipian","data":{"__id__":1}},{"__type__":"cc.Node","_name":"fragment","_children":[{"__id__":2},{"__id__":3},{"__id__":4}],"_prefab":{"__type__":"cc.PrefabInfo","root":{"__id__":1},"asset":{"__uuid__":"44EE+mPMRDwqNQTvV6VTZn"},"fileId":"cdw0n2NvtBWoLRbs03330D"},"_trs":{"__type__":"TypedArray","ctor":"Float64Array","array":[0,0,0,0,0,0,1,1,1,1]}},{"__type__":"cc.Node","_name":"New Particle","_parent":{"__id__":1},"_components":[{"__type__":"cc.ParticleSystem","node":{"__id__":2},"_materials":[{"__uuid__":"ecpdLyjvZBwrvm+cedCcQy"}],"_dstBlendFactor":1,"_custom":true,"_file":{"__uuid__":"b2aHrECZ5APKGS/0d2hvT1"},"_spriteFrame":{"__uuid__":"47LfXTNedBhJ5sf0G+5l7j"},"_stopped":false,"totalParticles":200,"emissionRate":300,"life":0.20000000298023224,"lifeVar":0.1,"_startColor":{"__type__":"cc.Color","r":241,"g":255,"b":83},"_startColorVar":{"__type__":"cc.Color"},"_endColor":{"__type__":"cc.Color","r":255,"g":248,"b":88},"_endColorVar":{"__type__":"cc.Color"},"angle":360,"angleVar":360,"startSize":3.369999885559082,"startSizeVar":50,"endSize":30.31999969482422,"startSpin":-47.369998931884766,"endSpin":-47.369998931884766,"endSpinVar":-142.11000061035156,"posVar":{"__type__":"cc.Vec2","x":2,"y":2},"gravity":{"__type__":"cc.Vec2","x":0.25,"y":0.8600000143051147},"speed":0,"speedVar":190.7899932861328,"tangentialAccel":-92.11000061035156,"tangentialAccelVar":65.79000091552734,"radialAccel":-671.0499877929688,"radialAccelVar":65.79000091552734}],"_prefab":{"__type__":"cc.PrefabInfo","root":{"__id__":1},"asset":{"__uuid__":"44EE+mPMRDwqNQTvV6VTZn"},"fileId":"67Izj0bylDcbJAQAjYUyQj"},"_trs":{"__type__":"TypedArray","ctor":"Float64Array","array":[0,0,0,0,0,0,1,1,1,1]}},{"__type__":"cc.Node","_name":"New Particle copy","_parent":{"__id__":1},"_components":[{"__type__":"cc.ParticleSystem","node":{"__id__":3},"_materials":[{"__uuid__":"ecpdLyjvZBwrvm+cedCcQy"}],"_dstBlendFactor":1,"_custom":true,"_file":{"__uuid__":"b2aHrECZ5APKGS/0d2hvT1"},"_spriteFrame":{"__uuid__":"47LfXTNedBhJ5sf0G+5l7j"},"_stopped":false,"totalParticles":15,"emissionRate":300,"life":0.20000000298023224,"lifeVar":0.1,"_startColor":{"__type__":"cc.Color","r":241,"g":255,"b":83},"_startColorVar":{"__type__":"cc.Color"},"_endColor":{"__type__":"cc.Color","r":255,"g":248,"b":88},"_endColorVar":{"__type__":"cc.Color"},"angle":360,"angleVar":360,"startSize":3.369999885559082,"startSizeVar":30,"endSize":10,"startSpin":-47.369998931884766,"endSpin":-47.369998931884766,"endSpinVar":-142.11000061035156,"posVar":{"__type__":"cc.Vec2","x":2,"y":2},"gravity":{"__type__":"cc.Vec2","x":0.25,"y":0.8600000143051147},"speed":0,"speedVar":190.7899932861328,"tangentialAccel":-92.11000061035156,"tangentialAccelVar":65.79000091552734,"radialAccel":-671.0499877929688,"radialAccelVar":65.79000091552734}],"_prefab":{"__type__":"cc.PrefabInfo","root":{"__id__":1},"asset":{"__uuid__":"44EE+mPMRDwqNQTvV6VTZn"},"fileId":"42c17GeI5Nw7OrrAc2UQbW"},"_trs":{"__type__":"TypedArray","ctor":"Float64Array","array":[0,0,0,0,0,0,1,1,1,1]}},{"__type__":"cc.Node","_name":"spr","_parent":{"__id__":1},"_components":[{"__type__":"cc.Sprite","node":{"__id__":4},"_materials":[{"__uuid__":"ecpdLyjvZBwrvm+cedCcQy"}],"_spriteFrame":{"__uuid__":"5fcpEKiw5PxKr4y93eBM+x"}}],"_prefab":{"__type__":"cc.PrefabInfo","root":{"__id__":1},"asset":{"__uuid__":"44EE+mPMRDwqNQTvV6VTZn"},"fileId":"cdb633BaZHdY9EWWFBiqyP"},"_contentSize":{"__type__":"cc.Size","width":78,"height":63},"_trs":{"__type__":"TypedArray","ctor":"Float64Array","array":[0,0,0,0,0,0,1,1,1,1]}}],{"__type__":"cc.SpriteFrame","content":{"name":"atom","texture":"d0qC05vt5GxLaYyB/w3t//","rect":[0,0,31,31],"offset":[0,0],"originalSize":[31,31],"capInsets":[0,0,0,0]}},{"__type__":"cc.SpriteFrame","content":{"name":"fragment","texture":"18Z/0WopVAB611NvoSQ8q+","rect":[0,0,78,63],"offset":[0,0],"originalSize":[78,63],"capInsets":[0,0,0,0]}}]